{
  "agg": {
    "losers": 2,
    "n": 15,
    "unrealized_r": 8.2696,
    "winners": 13
  },
  "trades": {
    "35189947": {
      "dl_soon": false,
      "health": "healthy",
      "status": "pending",
      "stop_touched": false,
      "symbol": "BTCUSDT",
      "tp1_filled": false,
      "tp1_touched": false,
      "ur": 0.1920568914125342
    },
    "37c92910": {
      "dl_soon": false,
      "health": "healthy",
      "status": "pending",
      "stop_touched": false,
      "symbol": "LINKUSDT",
      "tp1_filled": true,
      "tp1_touched": true,
      "ur": 0.9770459081836278
    },
    "3a945fb3": {
      "dl_soon": false,
      "health": "healthy",
      "status": "pending",
      "stop_touched": false,
      "symbol": "BNBUSDT",
      "tp1_filled": false,
      "tp1_touched": false,
      "ur": 0.5857573190247637
    },
    "4aa6dacc": {
      "dl_soon": false,
      "health": "healthy",
      "status": "pending",
      "stop_touched": false,
      "symbol": "BNBUSDT",
      "tp1_filled": false,
      "tp1_touched": false,
      "ur": 0.5857573190247637
    },
    "5866e4d7": {
      "dl_soon": false,
      "health": "healthy",
      "status": "pending",
      "stop_touched": false,
      "symbol": "ADAUSDT",
      "tp1_filled": true,
      "tp1_touched": true,
      "ur": 0.8896713615023694
    },
    "8267bb69": {
      "dl_soon": false,
      "health": "healthy",
      "status": "pending",
      "stop_touched": false,
      "symbol": "ADAUSDT",
      "tp1_filled": false,
      "tp1_touched": false,
      "ur": 0.3450106157112553
    },
    "89b155da": {
      "dl_soon": false,
      "health": "healthy",
      "status": "pending",
      "stop_touched": false,
      "symbol": "AVAXUSDT",
      "tp1_filled": false,
      "tp1_touched": true,
      "ur": 1.207434052757792
    },
    "906444ba": {
      "dl_soon": false,
      "health": "healthy",
      "status": "pending",
      "stop_touched": false,
      "symbol": "DOTUSDT",
      "tp1_filled": false,
      "tp1_touched": false,
      "ur": 0.7156862745098025
    },
    "91260541": {
      "dl_soon": false,
      "health": "healthy",
      "status": "pending",
      "stop_touched": false,
      "symbol": "LINKUSDT",
      "tp1_filled": false,
      "tp1_touched": false,
      "ur": 0.2641791044776094
    },
    "9480caef": {
      "dl_soon": false,
      "health": "healthy",
      "status": "pending",
      "stop_touched": false,
      "symbol": "DOGEUSDT",
      "tp1_filled": true,
      "tp1_touched": true,
      "ur": 1.944444444444442
    },
    "9b8dcacd": {
      "dl_soon": false,
      "health": "healthy",
      "status": "pending",
      "stop_touched": false,
      "symbol": "BTCUSDT",
      "tp1_filled": false,
      "tp1_touched": false,
      "ur": 0.18736423219725876
    },
    "9e5d97b9": {
      "dl_soon": false,
      "health": "healthy",
      "status": "pending",
      "stop_touched": false,
      "symbol": "XRPUSDT",
      "tp1_filled": false,
      "tp1_touched": false,
      "ur": -0.013841486537720219
    },
    "b1a6f80e": {
      "dl_soon": false,
      "health": "healthy",
      "status": "pending",
      "stop_touched": false,
      "symbol": "DOTUSDT",
      "tp1_filled": false,
      "tp1_touched": false,
      "ur": 0.7156862745098025
    },
    "fdbebcca": {
      "dl_soon": false,
      "health": "warning",
      "status": "pending",
      "stop_touched": false,
      "symbol": "ETHUSDT",
      "tp1_filled": false,
      "tp1_touched": false,
      "ur": -0.41788042724372015
    },
    "ff3145ff": {
      "dl_soon": false,
      "health": "healthy",
      "status": "pending",
      "stop_touched": false,
      "symbol": "ETHUSDT",
      "tp1_filled": false,
      "tp1_touched": false,
      "ur": 0.09125188536953524
    }
  }
}