{
  "agg": {
    "losers": 1,
    "n": 5,
    "unrealized_r": 2.8593,
    "winners": 3
  },
  "trades": {
    "52cc0d6b": {
      "dl_soon": false,
      "health": "healthy",
      "status": "pending",
      "stop_touched": false,
      "symbol": "DOGEUSDT",
      "tp1_filled": false,
      "tp1_touched": false,
      "ur": 0.9242108914325452
    },
    "690f206a": {
      "dl_soon": false,
      "health": "healthy",
      "status": "pending",
      "stop_touched": false,
      "symbol": "DOTUSDT",
      "tp1_filled": false,
      "tp1_touched": false,
      "ur": 0.9498834498834456
    },
    "afdf848d": {
      "dl_soon": false,
      "health": "healthy",
      "status": "pending",
      "stop_touched": false,
      "symbol": "BTCUSDT",
      "tp1_filled": false,
      "tp1_touched": false,
      "ur": -0.05581675385742717
    },
    "c896bc30": {
      "dl_soon": false,
      "health": "healthy",
      "status": "pending",
      "stop_touched": false,
      "symbol": "DOGEUSDT",
      "tp1_filled": false,
      "tp1_touched": false,
      "ur": 1.041008276899932
    },
    "dfa7997d": {
      "dl_soon": false,
      "health": "pending",
      "status": "pending",
      "stop_touched": false,
      "symbol": "DOTUSDT",
      "tp1_filled": false,
      "tp1_touched": false,
      "ur": null
    }
  }
}