{
  "agg": {
    "losers": 1,
    "n": 6,
    "unrealized_r": 1.9185,
    "winners": 5
  },
  "trades": {
    "3318d7c1": {
      "dl_soon": false,
      "health": "healthy",
      "status": "pending",
      "stop_touched": false,
      "symbol": "AVAXUSDT",
      "tp1_filled": false,
      "tp1_touched": false,
      "ur": -0.0947441217150736
    },
    "5756f497": {
      "dl_soon": false,
      "health": "healthy",
      "status": "pending",
      "stop_touched": false,
      "symbol": "DOTUSDT",
      "tp1_filled": false,
      "tp1_touched": false,
      "ur": 0.3717948717948693
    },
    "6a2c9bbf": {
      "dl_soon": false,
      "health": "healthy",
      "status": "pending",
      "stop_touched": false,
      "symbol": "DOTUSDT",
      "tp1_filled": false,
      "tp1_touched": false,
      "ur": 0.47777777777777675
    },
    "a4066b14": {
      "dl_soon": false,
      "health": "healthy",
      "status": "pending",
      "stop_touched": false,
      "symbol": "AVAXUSDT",
      "tp1_filled": false,
      "tp1_touched": false,
      "ur": 0.604000000000004
    },
    "b1e12e8e": {
      "dl_soon": false,
      "health": "healthy",
      "status": "pending",
      "stop_touched": false,
      "symbol": "DOGEUSDT",
      "tp1_filled": false,
      "tp1_touched": false,
      "ur": 0.2887323943661872
    },
    "d4271264": {
      "dl_soon": false,
      "health": "healthy",
      "status": "pending",
      "stop_touched": false,
      "symbol": "DOGEUSDT",
      "tp1_filled": false,
      "tp1_touched": false,
      "ur": 0.2709497206703847
    }
  }
}