{
  "agg": {
    "losers": 4,
    "n": 7,
    "unrealized_r": -0.0497,
    "winners": 3
  },
  "trades": {
    "0ba38651": {
      "dl_soon": false,
      "health": "warning",
      "status": "pending",
      "stop_touched": false,
      "symbol": "LINKUSDT",
      "tp1_filled": false,
      "tp1_touched": false,
      "ur": -0.4555555555555434
    },
    "21d17f15": {
      "dl_soon": false,
      "health": "healthy",
      "status": "pending",
      "stop_touched": false,
      "symbol": "ETHUSDT",
      "tp1_filled": false,
      "tp1_touched": false,
      "ur": 0.20201183431953085
    },
    "37f240be": {
      "dl_soon": false,
      "health": "healthy",
      "status": "pending",
      "stop_touched": false,
      "symbol": "ETHUSDT",
      "tp1_filled": false,
      "tp1_touched": false,
      "ur": 0.7828977533241674
    },
    "3b062ab5": {
      "dl_soon": false,
      "health": "near stop",
      "status": "pending",
      "stop_touched": false,
      "symbol": "AVAXUSDT",
      "tp1_filled": false,
      "tp1_touched": false,
      "ur": -0.7313354363827532
    },
    "41cf1a8d": {
      "dl_soon": false,
      "health": "warning",
      "status": "pending",
      "stop_touched": false,
      "symbol": "BTCUSDT",
      "tp1_filled": false,
      "tp1_touched": false,
      "ur": -0.6837341589068913
    },
    "6c3554aa": {
      "dl_soon": false,
      "health": "healthy",
      "status": "pending",
      "stop_touched": false,
      "symbol": "XRPUSDT",
      "tp1_filled": false,
      "tp1_touched": false,
      "ur": -0.06879233823873303
    },
    "f8bec027": {
      "dl_soon": false,
      "health": "healthy",
      "status": "pending",
      "stop_touched": false,
      "symbol": "BTCUSDT",
      "tp1_filled": false,
      "tp1_touched": false,
      "ur": 0.904853112340936
    }
  }
}