{
  "agg": {
    "losers": 1,
    "n": 4,
    "unrealized_r": 0.6992,
    "winners": 3
  },
  "trades": {
    "312570e6": {
      "dl_soon": false,
      "health": "healthy",
      "status": "pending",
      "stop_touched": false,
      "symbol": "SOLUSDT",
      "tp1_filled": false,
      "tp1_touched": false,
      "ur": 0.25047619047619
    },
    "6399f879": {
      "dl_soon": false,
      "health": "healthy",
      "status": "pending",
      "stop_touched": false,
      "symbol": "BTCUSDT",
      "tp1_filled": false,
      "tp1_touched": false,
      "ur": 0.292300268046394
    },
    "76675871": {
      "dl_soon": false,
      "health": "healthy",
      "status": "pending",
      "stop_touched": false,
      "symbol": "AVAXUSDT",
      "tp1_filled": false,
      "tp1_touched": false,
      "ur": -0.1936597614563766
    },
    "b9265a5e": {
      "dl_soon": false,
      "health": "healthy",
      "status": "pending",
      "stop_touched": false,
      "symbol": "ETHUSDT",
      "tp1_filled": false,
      "tp1_touched": false,
      "ur": 0.3500674051931302
    }
  }
}